LICENSE
MANIFEST.in
README.rst
setup.py
kippo_extra/__init__.py
kippo_extra/loader.py
kippo_extra/utils.py
kippo_extra.egg-info/PKG-INFO
kippo_extra.egg-info/SOURCES.txt
kippo_extra.egg-info/dependency_links.txt
kippo_extra.egg-info/top_level.txt
kippo_extra/commands/__init__.py
kippo_extra/commands/env.py
kippo_extra/commands/gcc.py
kippo_extra/commands/iptables.py
kippo_extra/commands/netstat.py
kippo_extra/commands/sleep.py
kippo_extra/commands/uname.py
kippo_extra/commands/which.py
kippo_extra/patches/kippo_core_honeypot.patch
kippo_extra/patches/kippo_core_protocol.patch