Metadata-Version: 1.1
Name: kippo-extra
Version: 1.1.0
Summary: Set of extra commands for the kippo SSH honeypot daemon
Home-page: https://github.com/basilfx/kippo-extra
Author: Bas Stottelaar
Author-email: basstottelaar@gmail.com
License: Copyright (c) 2013-2015 Bas Stottelaar
